rantoniuk/cloudwatch_retention_setter/__init__.py
rantoniuk/cloudwatch_retention_setter/py.typed
rantoniuk/cloudwatch_retention_setter/_jsii/__init__.py
rantoniuk/cloudwatch_retention_setter/_jsii/cloudwatch-retention-setter@1.0.0.jsii.tgz
rantoniuk.cloudwatch_retention_setter-1.0.0.dist-info/LICENSE
rantoniuk.cloudwatch_retention_setter-1.0.0.dist-info/METADATA
rantoniuk.cloudwatch_retention_setter-1.0.0.dist-info/WHEEL
rantoniuk.cloudwatch_retention_setter-1.0.0.dist-info/top_level.txt
rantoniuk.cloudwatch_retention_setter-1.0.0.dist-info/RECORD
